validator/__init__.py
validator/exceptions.py
validator/rule_pipe_validator.py
validator/rules.py
validator/rules_wrapper.py
validator/utils.py
validator/validator.py
validator/parser/__init__.py
validator/parser/parser.py
validator/parser/translator.py
validator/rules_src/__init__.py
validator/rules_src/accepted.py
validator/rules_src/alpha.py
validator/rules_src/base32.py
validator/rules_src/base64.py
validator/rules_src/between.py
validator/rules_src/binary.py
validator/rules_src/date.py
validator/rules_src/decimal.py
validator/rules_src/dict.py
validator/rules_src/hex.py
validator/rules_src/integer.py
validator/rules_src/ip.py
validator/rules_src/ipv4.py
validator/rules_src/ipv6.py
validator/rules_src/json.py
validator/rules_src/list.py
validator/rules_src/mail.py
validator/rules_src/max.py
validator/rules_src/min.py
validator/rules_src/octal.py
validator/rules_src/regex.py
validator/rules_src/required.py
validator/rules_src/required_if.py
validator/rules_src/same.py
validator/rules_src/size.py
validator/rules_src/string.py
validator/rules_src/uuidv1.py
validator/rules_src/uuidv3.py
validator/rules_src/uuidv4.py
validator-0.7.1.dist-info/LICENSE
validator-0.7.1.dist-info/METADATA
validator-0.7.1.dist-info/WHEEL
validator-0.7.1.dist-info/top_level.txt
validator-0.7.1.dist-info/RECORD
