Metadata-Version: 2.1
Name: validator
Version: 0.7.1
Summary: Python Validator
Home-page: https://github.com/CSenshi/Validator
Author: Saba Pockhua
Author-email: saba.pochkhua@gmail.com
License: MIT
Platform: UNKNOWN
Classifier: Programming Language :: Python :: 3.6
Classifier: Programming Language :: Python :: 3.7
Classifier: Programming Language :: Python :: 3.8
Classifier: License :: OSI Approved :: MIT License
Classifier: Operating System :: OS Independent
